helloworld.py
helloworld_nmoore-0.0.1.dist-info/LICENSE.txt
helloworld_nmoore-0.0.1.dist-info/METADATA
helloworld_nmoore-0.0.1.dist-info/WHEEL
helloworld_nmoore-0.0.1.dist-info/top_level.txt
helloworld_nmoore-0.0.1.dist-info/RECORD
